bootstrap/__init__.py
bootstrap/bootstrap.py
bootstrap/datasets.py
bootstrap/extensions.py
bootstrap/py.typed
pandas_bootstrap-0.3.0.dist-info/METADATA
pandas_bootstrap-0.3.0.dist-info/WHEEL
pandas_bootstrap-0.3.0.dist-info/licenses/LICENSE
pandas_bootstrap-0.3.0.dist-info/RECORD
