Metadata-Version: 2.4
Name: pandas-bootstrap
Version: 0.3.0
Summary: Statistical Bootstrap with Pandas made easy
Project-URL: Homepage, https://williambdean.github.io/pandas-bootstrap/
Project-URL: Repository, https://github.com/williambdean/pandas-bootstrap
Project-URL: Documentation, https://williambdean.github.io/pandas-bootstrap/
Author-email: Will Dean <wd60622@gmail.com>
License-Expression: MIT
License-File: LICENSE
Classifier: Intended Audience :: Science/Research
Classifier: Operating System :: OS Independent
Classifier: Programming Language :: Cython
Classifier: Programming Language :: Python
Classifier: Programming Language :: Python :: 3
Classifier: Programming Language :: Python :: 3 :: Only
Classifier: Programming Language :: Python :: 3.9
Classifier: Programming Language :: Python :: 3.10
Classifier: Programming Language :: Python :: 3.11
Classifier: Programming Language :: Python :: 3.12
Classifier: Programming Language :: Python :: 3.13
Classifier: Topic :: Scientific/Engineering
Requires-Python: <4.0,>=3.9
Requires-Dist: joblib<2,>=1.1.1
Requires-Dist: pandas>=1.0.0
Requires-Dist: typing-extensions; python_version < '3.10'
